Metadata-Version: 1.1
Name: sc-downloader
Version: 0.3.1
Summary: Downloads music from Soundcloud.
Home-page: https://github.com/WORD559/snapchat-downloader
Author: WORD559
Author-email: josh.barrass.work@gmail.com
License: UNKNOWN
Keywords: soundcloud downloader music archive dump
Platform: UNKNOWN
Classifier: Intended Audience :: Developers
Classifier: Natural Language :: English
Classifier: Programming Language :: Python :: 2
